src/__init__.py
src/config.py
src/downloader.py
src/errors.py
src/main.py
src/memory.json
src/models.py
src/pyproject.toml
src/spider.py
src/utils.py
download_from_stupid_emby-0.0.0.dist-info/METADATA
download_from_stupid_emby-0.0.0.dist-info/WHEEL
download_from_stupid_emby-0.0.0.dist-info/RECORD
