Metadata-Version: 2.1
Name: download-from-stupid-emby
Version: 0.0.0
Summary: 稳定的EMBY服资源下载器
Author: lengmianzz
Requires-Python: >=3.10,<4.0
Classifier: Programming Language :: Python :: 3
Classifier: Programming Language :: Python :: 3.10
Classifier: Programming Language :: Python :: 3.11
Classifier: Programming Language :: Python :: 3.12
Requires-Dist: httpx (>=0.27.0,<0.28.0)
Requires-Dist: loguru (>=0.7.2,<0.8.0)
Requires-Dist: pydantic (>=2.8.2,<3.0.0)
Requires-Dist: tomlkit (>=0.12.5,<0.13.0)
Requires-Dist: tqdm (>=4.66.4,<5.0.0)
